dockerma/__init__.py
dockerma/build.py
dockerma/cache.py
dockerma/docker.py
dockerma/image.py
dockerma/push.py
dockerma-0.5.6.dist-info/LICENSE
dockerma-0.5.6.dist-info/METADATA
dockerma-0.5.6.dist-info/WHEEL
dockerma-0.5.6.dist-info/entry_points.txt
dockerma-0.5.6.dist-info/top_level.txt
dockerma-0.5.6.dist-info/zip-safe
dockerma-0.5.6.dist-info/RECORD
