Metadata-Version: 2.1
Name: dockerma
Version: 0.5.6
Summary: DockerMA facilitates building multi-arch containers with minimal fuss
Home-page: https://github.com/mortenlj/dockerma
Author: Morten Lied Johansen
Author-email: mortenjo@ifi.uio.no
License: The MIT License
Project-URL: Source, https://github.com/mortenlj/dockerma/src
Project-URL: Tracker, https://github.com/mortenlj/dockerma/issues
Keywords: docker
Platform: UNKNOWN
Classifier: Development Status :: 3 - Alpha
Classifier: Environment :: Console
Classifier: Intended Audience :: Developers
Classifier: License :: OSI Approved :: MIT License
Classifier: Operating System :: POSIX :: Linux
Classifier: Programming Language :: Python
Classifier: Programming Language :: Python :: 2
Classifier: Programming Language :: Python :: 2.7
Classifier: Programming Language :: Python :: 3
Classifier: Programming Language :: Python :: 3.5
Classifier: Programming Language :: Python :: 3.6
Classifier: Programming Language :: Python :: 3.7
Classifier: Topic :: Software Development
Classifier: Topic :: Software Development :: Build Tools
Classifier: Topic :: System :: Software Distribution
Classifier: Topic :: Utilities
Requires-Dist: appdirs (==1.4.3)
Requires-Dist: six
Provides-Extra: ci
Requires-Dist: tox ; extra == 'ci'
Requires-Dist: tox-gh-actions ; extra == 'ci'
Requires-Dist: publish ; extra == 'ci'
Provides-Extra: dev
Requires-Dist: pytest-html (==1.19.0) ; extra == 'dev'
Requires-Dist: pytest-cov (==2.6.0) ; extra == 'dev'
Requires-Dist: pytest (==3.8.2) ; extra == 'dev'
Requires-Dist: mock (==3.0.5) ; extra == 'dev'
Requires-Dist: tox ; extra == 'dev'
Requires-Dist: tox-gh-actions ; extra == 'dev'
Requires-Dist: publish ; extra == 'dev'
